CVUtils.py
CVUtils/CVUtils.py
CVUtils/__init__.py
CVUtils/test.py
CVUtils/files/WordAndNum.txt
CVUtils/files/province.txt
MingLogCVUtils-1.0.3.dist-info/LICENSE
MingLogCVUtils-1.0.3.dist-info/METADATA
MingLogCVUtils-1.0.3.dist-info/WHEEL
MingLogCVUtils-1.0.3.dist-info/top_level.txt
MingLogCVUtils-1.0.3.dist-info/RECORD
